ceair_helper/__init__.py
ceair_helper/config/__init__.py
ceair_helper/config/url_const.py
ceair_helper/controller/__init__.py
ceair_helper/controller/booking_flight.py
ceair_helper/controller/my_order_query.py
ceair_helper/controller/order_payment.py
ceair_helper/controller/user_login.py
ceair_helper/controller/web_ticket_checkout_flow.py
ceair_helper/po/__init__.py
ceair_helper/po/add_sercies_page.py
ceair_helper/po/booking_new_page.py
ceair_helper/po/cashier_desk_web_page_detail_page.py
ceair_helper/po/login_page.py
ceair_helper/po/main_page.py
ceair_helper/po/my_ticket_order_detail_page.py
ceair_helper/po/my_ticket_order_page.py
ceair_helper/po/one_way_page.py
ceair_helper/po/payment_page.py
python_ceair_helper-0.2.4.dist-info/licenses/LICENSE
python_ceair_helper-0.2.4.dist-info/METADATA
python_ceair_helper-0.2.4.dist-info/WHEEL
python_ceair_helper-0.2.4.dist-info/top_level.txt
python_ceair_helper-0.2.4.dist-info/RECORD
