Metadata-Version: 2.4
Name: python_ceair_helper
Version: 0.2.4
Summary: ceair helper python package
Author-email: ckf10000 <ckf10000@sina.com>
License:                                  Apache License
Project-URL: Homepage, https://github.com/ckf10000/python-ceair-helper
Project-URL: Source, https://github.com/ckf10000/python-ceair-helper
Project-URL: Issues, https://github.com/ckf10000/python-ceair-helper/issues
Requires-Python: >=3.12
License-File: LICENSE
Requires-Dist: python_playwright_helper>=0.3.0
Dynamic: license-file
